MANIFEST.in
README.md
setup.py
pylinweb/__init__.py
pylinweb/functions.py
pylinweb/main.py
pylinweb/variables.py
pylinweb.egg-info/PKG-INFO
pylinweb.egg-info/SOURCES.txt
pylinweb.egg-info/dependency_links.txt
pylinweb.egg-info/entry_points.txt
pylinweb.egg-info/requires.txt
pylinweb.egg-info/top_level.txt