Metadata-Version: 2.1
Name: pylinweb
Version: 1.9.4
Summary: A simple functional test library using Python and Selenium
Author: Linda Lopez
Keywords: selenium,testing,web,chrome
Classifier: Development Status :: 3 - Alpha
Classifier: Intended Audience :: Developers
Classifier: License :: OSI Approved :: MIT License
Classifier: Programming Language :: Python
Requires-Dist: allure-behave==2.13.5
Requires-Dist: allure-python-commons==2.13.5
Requires-Dist: behave==1.2.6
Requires-Dist: behave-html-formatter==0.9.10
Requires-Dist: behave2cucumber==1.0.3
Requires-Dist: docxcompose==1.4.0
Requires-Dist: docxtpl==0.16.8
Requires-Dist: playwright==1.42.0
Requires-Dist: psutil==5.9.2
Requires-Dist: PyPDF2==3.0.1
Requires-Dist: python-docx==1.1.0
Requires-Dist: pycparser==2.21
Requires-Dist: screeninfo==0.8
Requires-Dist: selenium==4.12
Requires-Dist: keyboard==0.13.5
